dig/__init__.py
dig/dio.py
dig/utilvar.py
dig_mhd-0.0.1.dist-info/LICENSE
dig_mhd-0.0.1.dist-info/METADATA
dig_mhd-0.0.1.dist-info/WHEEL
dig_mhd-0.0.1.dist-info/top_level.txt
dig_mhd-0.0.1.dist-info/RECORD
