Metadata-Version: 2.1
Name: dig-mhd
Version: 0.0.1
Summary: Dig, short for diagnostic, is used to help acquire diagnostic data from MDSplus. 
Home-page: https://github.com/WenyinWei/dig
Author: Wenyin Wei
Author-email: wenyin.wei.ww@gmail.com
Classifier: Development Status :: 2 - Pre-Alpha
Classifier: Programming Language :: Python :: 3
Classifier: License :: OSI Approved :: GNU General Public License v3 or later (GPLv3+)
Classifier: Operating System :: OS Independent
Requires-Python: >=3.8
License-File: LICENSE
Requires-Dist: numpy
Requires-Dist: scipy
Requires-Dist: matplotlib
Requires-Dist: plotly
Requires-Dist: Deprecated
Requires-Dist: appdata
